{"_ts":[1577845284],"_r":{"breakdown":{"html":{"bytes":[87189],"requests":[4]},"js":{"bytes":[205658],"requests":[13]},"css":{"bytes":[10557],"requests":[6]},"image":{"bytes":[222190],"requests":[9]},"flash":{"bytes":[0],"requests":[0]},"font":{"bytes":[78588],"requests":[4]},"video":{"bytes":[0],"requests":[0]},"other":{"bytes":[0],"requests":[2]}},"date":[1577845284],"domElements":[408],"domInteractive":[1244],"firstPaint":[1114.7299999993],"fullyLoaded":[3904],"id":["200101_MS_53f84b49dcdfc894ed95b08dfbabb1e7"],"loadTime":[3172],"render":[1100],"SpeedIndex":[1365],"TTFB":[397],"videoFrames":[[{"_i":"ms_000000.jpg","_t":0,"_vc":0},{"_i":"ms_001100.jpg","_t":1100,"_vc":39},{"_i":"ms_001300.jpg","_t":1300,"_vc":38},{"_i":"ms_001400.jpg","_t":1400,"_vc":96},{"_i":"ms_001900.jpg","_t":1900,"_vc":96},{"_i":"ms_002800.jpg","_t":2800,"_vc":96},{"_i":"ms_002900.jpg","_t":2900,"_vc":97},{"_i":"ms_003100.jpg","_t":3100,"_vc":97},{"_i":"ms_003400.jpg","_t":3400,"_vc":97},{"_i":"ms_003500.jpg","_t":3500,"_vc":97},{"_i":"ms_003600.jpg","_t":3600,"_vc":100}]],"visualComplete":[3600],"lighthouse":[54],"pagespeed":[85]}}