{"_ts":[1559360006,1559404108,1559448184],"_r":{"breakdown":{"html":{"bytes":[36916,33853,33773],"requests":[7,7,7]},"js":{"bytes":[680042,649936,680042],"requests":[35,35,35]},"css":{"bytes":[170599,170599,170599],"requests":[2,2,2]},"image":{"bytes":[1817813,1685912,1699494],"requests":[27,31,30]},"flash":{"bytes":[0,0,0],"requests":[0,0,0]},"font":{"bytes":[125488,125488,125488],"requests":[7,7,7]},"video":{"bytes":[0,0,0],"requests":[0,0,0]},"other":{"bytes":[229,229,229],"requests":[9,9,9]}},"date":[1559360006,1559404108,1559448184],"domElements":[636,640,640],"domInteractive":[2284,2537,2520],"firstPaint":[1609.0399999957,1814.6699999998,1843.4000000007],"fullyLoaded":[7014,6608,6459],"id":["190601_XM_48393d15b016dcf94e7e5080f8ab15d5","190601_G5_7c2a4777c29562096a3758ab24e12bd7","190602_FY_fb5e3e69a3ba882c9d17a34f301aa505"],"loadTime":[6359,5828,5622],"render":[1600,1800,2000],"SpeedIndex":[2156,2277,2468],"TTFB":[470,452,437],"videoFrames":[[{"_i":"ms_000000.jpg","_t":0,"_vc":0},{"_i":"ms_001600.jpg","_t":1600,"_vc":86},{"_i":"ms_001800.jpg","_t":1800,"_vc":86},{"_i":"ms_002600.jpg","_t":2600,"_vc":86},{"_i":"ms_003300.jpg","_t":3300,"_vc":89},{"_i":"ms_003900.jpg","_t":3900,"_vc":89},{"_i":"ms_004100.jpg","_t":4100,"_vc":90},{"_i":"ms_004300.jpg","_t":4300,"_vc":90},{"_i":"ms_005700.jpg","_t":5700,"_vc":90},{"_i":"ms_006000.jpg","_t":6000,"_vc":90},{"_i":"ms_006300.jpg","_t":6300,"_vc":90},{"_i":"ms_006400.jpg","_t":6400,"_vc":100}],[{"_i":"ms_000000.jpg","_t":0,"_vc":0},{"_i":"ms_001800.jpg","_t":1800,"_vc":87},{"_i":"ms_002000.jpg","_t":2000,"_vc":87},{"_i":"ms_002300.jpg","_t":2300,"_vc":87},{"_i":"ms_002400.jpg","_t":2400,"_vc":86},{"_i":"ms_002800.jpg","_t":2800,"_vc":86},{"_i":"ms_003500.jpg","_t":3500,"_vc":87},{"_i":"ms_003600.jpg","_t":3600,"_vc":87},{"_i":"ms_004000.jpg","_t":4000,"_vc":90},{"_i":"ms_005100.jpg","_t":5100,"_vc":90},{"_i":"ms_005500.jpg","_t":5500,"_vc":90},{"_i":"ms_005800.jpg","_t":5800,"_vc":100}],[{"_i":"ms_000000.jpg","_t":0,"_vc":0},{"_i":"ms_002000.jpg","_t":2000,"_vc":86},{"_i":"ms_002100.jpg","_t":2100,"_vc":86},{"_i":"ms_002400.jpg","_t":2400,"_vc":86},{"_i":"ms_002500.jpg","_t":2500,"_vc":86},{"_i":"ms_002600.jpg","_t":2600,"_vc":85},{"_i":"ms_002900.jpg","_t":2900,"_vc":85},{"_i":"ms_003100.jpg","_t":3100,"_vc":86},{"_i":"ms_003500.jpg","_t":3500,"_vc":89},{"_i":"ms_003700.jpg","_t":3700,"_vc":89},{"_i":"ms_003900.jpg","_t":3900,"_vc":89},{"_i":"ms_004400.jpg","_t":4400,"_vc":89},{"_i":"ms_005500.jpg","_t":5500,"_vc":89},{"_i":"ms_005800.jpg","_t":5800,"_vc":100}]],"visualComplete":[6400,5800,5800],"lighthouse":[31,31,31],"pagespeed":[80,78,80]}}